qsci/__init__.py
qsci/pauliOperator.py
qsci/utils.py
qsci/applications/__init__.py
qsci/applications/greenfunction/LatticeGreen.py
qsci/applications/greenfunction/__init__.py
qsci/applications/greenfunction/frequencyGreenf.py
qsci/applications/greenfunction/retardedGreenfunction.py
qsci/fermionHamiltonian_deprecated/__init__.py
qsci/fermionHamiltonian_deprecated/jordanWigner.py
qsci/secondQuantization/__init__.py
qsci/secondQuantization/qubitEncoding.py
qsci/secondQuantization/hamiltonian/__init__.py
qsci/secondQuantization/hamiltonian/fermion.py
qsci/secondQuantization/hamiltonian/fermionLattice.py
qsci/tool/__init__.py
qsci/tool/diag.py
qsci/tool/integration.py
qsci/vqe/__init__.py
qsci/vqe/optimizer.py
qsci/vqe/pauliHamEnergy.py
qsci-0.0.3.dist-info/METADATA
qsci-0.0.3.dist-info/WHEEL
qsci-0.0.3.dist-info/top_level.txt
qsci-0.0.3.dist-info/RECORD
