Metadata-Version: 2.1
Name: qsci
Version: 0.0.3
Summary: High level application based on isqdeployer
Home-page: https://www.arclightquantum.com/
License: LICENSE.md
Requires-Python: >=3.7
Requires-Dist: isqdeployer (>=0.0.50)
Requires-Dist: matplotlib
Requires-Dist: rich
